Workbook

Sheet 📊 Dashboard
A1: AHF PHARMACY — ACHC RE-ACCREDITATION AUDIT WORKBOOK
A2: Onsite Visit Readiness Tracker | Jan 19 – Apr 17, 2026
A4: SECTION READINESS SUMMARY
A5: Section | B5: Standard Area | C5: Total Items | D5: Complete | E5: In Progress | F5: Gaps | G5: N/A | H5: % Ready
A6: Sec 1 | B6: Organization & Administration | C6: ='📋 Sec1 - Org & Admin'!B2 -> 8 | D6: ='📋 Sec1 - Org & Admin'!C2 -> 0 | E6: ='📋 Sec1 - Org & Admin'!D2 -> 0 | F6: ='📋 Sec1 - Org & Admin'!E2 -> 0 | G6: ='📋 Sec1 - Org & Admin'!F2 -> 0 | H6: =IFERROR(D6/(C6-G6),0) -> 0
A7: Sec 2 | B7: Program / Service Operations | C7: ='📋 Sec2 - Program Ops'!B2 -> 16 | D7: ='📋 Sec2 - Program Ops'!C2 -> 0 | E7: ='📋 Sec2 - Program Ops'!D2 -> 0 | F7: ='📋 Sec2 - Program Ops'!E2 -> 0 | G7: ='📋 Sec2 - Program Ops'!F2 -> 0 | H7: =IFERROR(D7/(C7-G7),0) -> 0
A8: Sec 3 | B8: Fiscal Management | C8: ='📋 Sec3 - Fiscal'!B2 -> 7 | D8: ='📋 Sec3 - Fiscal'!C2 -> 0 | E8: ='📋 Sec3 - Fiscal'!D2 -> 0 | F8: ='📋 Sec3 - Fiscal'!E2 -> 0 | G8: ='📋 Sec3 - Fiscal'!F2 -> 0 | H8: =IFERROR(D8/(C8-G8),0) -> 0
A9: Sec 4 | B9: Human Resources Management | C9: ='📋 Sec4 - HR'!B2 -> 14 | D9: ='📋 Sec4 - HR'!C2 -> 0 | E9: ='📋 Sec4 - HR'!D2 -> 0 | F9: ='📋 Sec4 - HR'!E2 -> 0 | G9: ='📋 Sec4 - HR'!F2 -> 0 | H9: =IFERROR(D9/(C9-G9),0) -> 0
A10: TOTALS | C10: =SUM(C6:C9) -> 45 | D10: =SUM(D6:D9) -> 0 | E10: =SUM(E6:E9) -> 0 | F10: =SUM(F6:F9) -> 0 | G10: =SUM(G6:G9) -> 0 | H10: =IFERROR(D10/(C10-G10),0) -> 0
A12: KEY VISIT INFORMATION
A13: Accrediting Body | B13: ACHC – Accreditation Commission for Healthcare, Inc.
A14: Visit Type | B14: Onsite Validation (4th round of accreditation)
A15: Visit Window | B15: January 19 – April 17, 2026
A16: Notice | B16: UNSCHEDULED – NO morning phone call in 2025 cycle
A17: # Locations Visited | B17: 23 AHF locations (new sites prioritized)
A18: Avoid Visits On | B18: Mondays (requested by AHF leadership)
A19: Compliance Officer | B19: Brandon Patchett, PharmD AAHIVP – Sr. Director Clinical Services
A20: Post-Visit SOF | B20: Summary of Findings sent to Corporate within 30 days
A21: Plan of Correction | B21: Drafted at Corporate w/ Pharmacy Director & Regional collaboration

Sheet 📋 Sec1 - Org & Admin
A1: ACHC RE-ACCREDITATION — SECTION 1: ORGANIZATION & ADMINISTRATION
B2: 8 | C2: =COUNTIF(F4:F11,"✅ Complete") -> 0 | D2: =COUNTIF(F4:F11,"⚠️ In Progress") -> 0 | E2: =COUNTIF(F4:F11,"❌ Gap") -> 0 | F2: =COUNTIF(F4:F11,"N/A") -> 0
A3: # | B3: ACHC Standard | C3: Requirement / What Surveyor Checks | D3: AHF Required Action | E3: Evidence / Document Needed | F3: Status | G3: Notes / Owner
A4: 1 | B4: DRX 1-1A/B | C4: Legal authority to operate; valid licensure, Articles of Incorporation on file | D4: Confirm federal, state, and local pharmacy licenses are current and accessible | E4: Current pharmacy licenses (state BOP, DEA, NPI); Articles of Incorporation | G4: Owner: _______________
A5: 2 | B5: DRX 1-2A | C5: Governing body/owner assumes full legal authority; duties clearly defined | D5: AHF governing body documentation reviewed and available | E5: Governing body bylaws or ownership documentation | G5: Owner: _______________
A6: 3 | B6: DRX 1-3A | C6: Written conflict-of-interest policy established and implemented | D6: Staff can identify where COI policy is located | E6: AHF COI Policy & Procedures; signed disclosures on file | G6: Owner: _______________
A7: 4 | B7: DRX 1-5A | C7: Org chart shows lines of authority for all positions; posted or easily retrievable at each site | D7: Post current Jan-2025 org chart in every pharmacy location | E7: Org chart posted on wall; URL: Dropbox link per Module 1 slide 13 | G7: Owner: _______________
A8: 5 | B8: DRX 1-7A | C8: Compliance with all applicable federal, state, and local laws and regulations | D8: Pharmacy Director aware of all active regulatory requirements | E8: State BOP inspection records; DMEPOS supplier standards compliance docs | G8: Owner: _______________
A9: 6 | B9: DRX 1-8A | C9: Organization complies with accepted professional standards of practice | D9: P&Ps align with current pharmacy practice standards | E9: Current P&P manual; date of last review | G9: Owner: _______________
A10: 7 | B10: DRX 1-9A | C10: CMS DMEPOS Supplier and Quality Standards compliance (Medicare/Medicaid billers) | D10: Patient Welcome Booklet provided to all new patients (pg. 7-10); marked in Initial Assessment | E10: Patient Welcome Booklet (English & Spanish); Initial Assessment form w/ checkbox | G10: Owner: _______________
A11: 8 | B11: DRX 1-10A | C11: Negative outcomes, sanctions, regulatory inspections reported to ACHC/CMS within 30 days | D11: Share all audit/inspection results with Pharmacy Regional → escalate to leadership | E11: Documentation of any regulatory findings; correspondence to ACHC/CMS | G11: Owner: _______________

Sheet 📋 Sec2 - Program Ops
A1: ACHC RE-ACCREDITATION — SECTION 2: PROGRAM / SERVICE OPERATIONS
B2: 16 | C2: =COUNTIF(F4:F19,"✅ Complete") -> 0 | D2: =COUNTIF(F4:F19,"⚠️ In Progress") -> 0 | E2: =COUNTIF(F4:F19,"❌ Gap") -> 0 | F2: =COUNTIF(F4:F19,"N/A") -> 0
A3: # | B3: ACHC Standard | C3: Requirement / What Surveyor Checks | D3: AHF Required Action | E3: Evidence / Document Needed | F3: Status | G3: Notes / Owner
A4: 1 | B4: DRX 2-1B | C4: Written P&P on description of care/services; patients informed of geographic area, pharmacist contact, Rx status, claims info, network status | D4: Ensure patients receive service description info at onboarding | E4: Patient Welcome Booklet; AHF Pharmacy website resources | G4: Owner: _______________
A5: 2 | B5: DRX 2-2A / 2-2A.01 | C5: Written P&P on Client/Patient Rights & Responsibilities distributed to all patients | D5: Provide Welcome Booklet to all new specialty patients; document in Initial Assessment | E5: Welcome Booklet pg. 14-16; Initial Assessment with 'provided' checkbox marked | G5: Owner: _______________
A6: 3 | B6: DRX 2-2B | C6: Organization actively protects and promotes patient rights | D6: Staff can describe how patient rights are upheld in practice | E6: P&P on patient rights; staff training documentation | G6: Owner: _______________
A7: 4 | B7: DRX 2-2C | C7: DMEPOS Supplier Standards distributed to each Medicare recipient | D7: Welcome Booklet provided; pg. 7-10 covers DMEPOS standards | E7: Welcome Booklet pg. 7-10; delivery/receipt documentation | G7: Owner: _______________
A8: 5 | B8: DRX 2-3A | C8: P&P for reporting/investigating mistreatment, neglect, verbal/sexual/physical abuse, misappropriation of patient property | D8: Staff know how to report abuse incidents; policy accessible | E8: AHF abuse reporting P&P; incident log; staff training records | G8: Owner: _______________
A9: 6 | B9: DRX 2-4A | C9: At initiation of care, patient informed how to report grievances/complaints and investigation process | D9: Communicate complaint process at patient intake; document in chart | E9: Welcome Booklet pg. 18; Initial Assessment documentation | G9: Owner: _______________
A10: 7 | B10: DRX 2-4B | C10: Medicare patients notified within 5 calendar days of receiving complaint (oral, phone, email, fax, or letter) | D10: If unable to resolve in-store, refer to Customer Care Line; document in SalesForce/RLDatix | E10: SalesForce/RLDatix complaint records; CCL referral documentation | G10: Owner: _______________
A11: 8 | B11: DRX 2-4C | C11: Patients have written info with phone number, contact person, and complaint resolution process | D11: Customer Care Line poster posted in public/waiting area (visible to patients) | E11: CCL poster on wall (855-894-MEDS); AHF Compliance Hotline 1-800-243-7448 | G11: Owner: _______________
A12: 9 | B12: DRX 2-5A | C12: Written P&P on securing and releasing PHI and ePHI; Notice of Privacy Practices | D12: Staff trained on PHI handling; Notice of Privacy Practices available to patients | E12: HIPAA P&P; Notice of Privacy Practices (posted/distributed); BAA for business associates | G12: Owner: _______________
A13: 10 | B13: DRX 2-5C | C13: Business Associate Agreements (BAAs) in place for all vendors with PHI access | D13: Confirm BAAs executed for all third-party vendors accessing patient data | E13: BAA log; executed BAA documents on file | G13: Owner: _______________
A14: 11 | B14: DRX 2-7A/B | C14: Written P&P on identification, evaluation, and discussion of ethical issues | D14: Staff aware of ethics policy; ethics training completed | E14: Ethics P&P; AHF U training completion records (annual) | G14: Owner: _______________
A15: 12 | B15: DRX 2-8A | C15: Written P&P for serving patients with communication or language barriers | D15: Language Line posted with instructions; staff know process; ScripTalk Reader available | E15: Language Line poster and instructions; ScripTalk Reader documentation | G15: Owner: _______________
... A19: 16 | B19: DRX 2-10F | C19: Toll-free number; phone system tracks call wait times, time to speak to clinician, abandonment rate | D19: Call metrics monitored monthly: ≤30 sec avg speed, ≤5% abandonment, ≥85% answered in 30 sec | E19: Monthly store stats report; Cisco call metrics dashboard | G19: Owner: _______________

Sheet 📋 Sec3 - Fiscal
A1: ACHC RE-ACCREDITATION — SECTION 3: FISCAL MANAGEMENT
B2: 7 | C2: =COUNTIF(F4:F10,"✅ Complete") -> 0 | D2: =COUNTIF(F4:F10,"⚠️ In Progress") -> 0 | E2: =COUNTIF(F4:F10,"❌ Gap") -> 0 | F2: =COUNTIF(F4:F10,"N/A") -> 0
A3: # | B3: ACHC Standard | C3: Requirement / What Surveyor Checks | D3: AHF Required Action | E3: Evidence / Document Needed | F3: Status | G3: Notes / Owner
A4: 1 | B4: DRX 3-1A | C4: Annual budget developed collaboratively with management/personnel under governing body direction | D4: AHF budget process documented; pharmacy leadership involved in budget development | E4: Annual budget documentation; meeting minutes showing pharmacy leadership participation | G4: Owner: _______________
A5: 2 | B5: DRX 3-2A | C5: Financial practices ensure accurate accounting and billing | D5: Accurate billing records maintained; coding and documentation align with dispensed services | E5: Billing records; pharmacy financial reconciliation reports | G5: Owner: _______________
A6: 3 | B6: DRX 3-4A | C6: Care/service rates established; charges communicated to patients, public, and referral sources | D6: Inform patients of co-pays, OOP costs, and deductibles PRIOR to processing any prescription | E6: Documentation of patient cost counseling in McKesson/Athena clinical notes | G6: Owner: _______________
A7: 4 | B7: DRX 3-4B | C7: Patient advised of financial responsibility before or at time of service; notified of changes within 30 days | D7: Inform patients of cost changes as soon as known; document Medication Access/Cost Consultation note in patient profile | E7: Medication Access/Cost Consultation clinical care notes in patient charts | G7: Owner: _______________
A8: 5 | B8: DRX 3-4C | C8: Mail-order patients advised of financial responsibility prior to receipt of service | D8: Patients notified of costs before processing mail-order prescriptions | E8: Pre-processing notification documentation; patient acknowledgment records | G8: Owner: _______________
A9: 6 | B9: DRX 3-5A | C9: Financial hardship forms completed for patients unable to pay | D9: Refer patient unable to pay to Pharmacy Director; work with HCC Benefits Counselor, Rx Sales Teams, PCM | E9: Completed financial hardship forms; referral documentation to benefits counselors | G9: Owner: _______________
A10: 7 | B10: DRX 3-6A | C10: Proper billing procedures followed including all prescription and documentation requirements specified by payor | D10: Ensure billing documentation matches dispensed medications; payor-specific requirements met | E10: Claims documentation; payor-specific billing requirement checklists | G10: Owner: _______________

Sheet 📋 Sec4 - HR
A1: ACHC RE-ACCREDITATION — SECTION 4: HR MANAGEMENT
B2: 14 | C2: =COUNTIF(F4:F17,"✅ Complete") -> 0 | D2: =COUNTIF(F4:F17,"⚠️ In Progress") -> 0 | E2: =COUNTIF(F4:F17,"❌ Gap") -> 0 | F2: =COUNTIF(F4:F17,"N/A") -> 0
A3: # | B3: ACHC Standard | C3: Requirement / What Surveyor Checks | D3: AHF Required Action | E3: Evidence / Document Needed | F3: Status | G3: Notes / Owner
A4: 1 | B4: DRX 4-2C | C4: All direct care staff have baseline TB test; annual symptom evaluation completed prior to patient contact | D4: Confirm TB test on file for all patient-facing staff upon hire; annual follow-up documented | E4: TB test results in HR personnel file; annual TB symptom evaluation records | G4: Owner: _______________
A5: 2 | B5: DRX 4-2D | C5: Direct care staff have access to Hepatitis B vaccine; offered per CDC/OSHA standards | D5: All patient-facing AHF staff offered Hep B vaccine; acceptance or declination documented | E5: Hep B vaccination records or signed declination forms in HR files | G5: Owner: _______________
A6: 3 | B6: DRX 4-2E | C6: Job description for each position consistent with org chart function and reporting structure | D6: Current job descriptions on file for all positions; match org chart | E6: Current job descriptions; org chart alignment documentation | G6: Owner: _______________
A7: 4 | B7: DRX 4-2F | C7: Motor vehicle records (MVR) checked at hire and annually for CDL-required drivers | D7: PSL drivers: copy of driver license in pharmacy Regulatory Binder and/or with PSL Hub Manager | E7: MVR check records; PSL driver license copies in Regulatory Binder | G7: Owner: _______________
A8: 5 | B8: DRX 4-2I | C8: Written personnel policies/employee handbook established; accessible to all staff | D8: All staff familiar with AHF Employee Handbook; accessible via AHF Connect Home Page | E8: AHF Employee Handbook; AHF Connect access documentation | G8: Owner: _______________
A9: 6 | B9: DRX 4-2J | C9: Written annual performance evaluations completed for all staff based on job description; results shared with employee | D9: Complete annual evaluations for all staff; review with employee and document | E9: Completed annual performance evaluation forms; signed acknowledgment by employee | G9: Owner: _______________
A10: 7 | B10: DRX 4-6A/B | C10: Written orientation process documented; all personnel documentation reflects orientation completed | D10: New hires complete AHF U New Hire Orientation within 30 days of hire; AHF Pharmacy Orientation course completed | E10: AHF U completion records; on-boarding checklist signed (kept in pharmacy and/or HR file) | G10: Owner: _______________
A11: 8 | B11: DRX 4-7A | C11: Competency assessment program designed for all personnel handling medications, equipment, and supplies | D11: Pharmacy Director conducts routine and random competency verifications; initial and annual assessments | E11: Completed competency assessment forms (hire + annual); Pharmacy Director documentation | G11: Owner: _______________
A12: 9 | B12: DRX 4-8A/B | C12: Written education plan defines content, frequency, and ongoing in-service training by staff classification | D12: All AHF U courses completed by due date; 30-60-90 day evaluations completed for new hires | E12: AHF U training completion records; 30-60-90 day evaluation forms on file | G12: Owner: _______________
A13: 10 | B13: DRX 4-9C | C13: Supervision available during all hours care/service is provided | D13: Pharmacist always present in pharmacy; emergency: contact Pharmacy Leadership immediately | E13: Schedule documentation; CCL after-hours coverage records | G13: Owner: _______________
A14: 11 | B14: DRX 4-9D | C14: Registered Pharmacist available 24/7 per patient plan of care | D14: After-hours calls forwarded to CRC-West Pharmacists; CCL provides 24/7 access | E14: CCL operational documentation; after-hours call routing policy | G14: Owner: _______________
A15: 12 | B15: DRX 4-14C | C15: Written P&P: Registered Pharmacist supervises pharmacy technicians per state BOP rules | D15: Ensure pharmacist supervision documented per state-specific requirements | E15: Supervision P&P; state BOP pharmacist-to-tech ratio documentation | G15: Owner: _______________
... A17: 14 | B17: DRX 4-15B | C17: Mail-order/specialty pharmacy has access to reference library and/or internet | D17: All pharmacists and staff have access to Facts & Comparison + UpToDate | E17: UpToDate and Facts & Comparison access credentials/subscriptions confirmed | G17: Owner: _______________

Sheet 🎤 Staff Interview Prep
A1: STAFF INTERVIEW PREP — KEY Q&A FOR ACHC ONSITE
A2: All staff levels. Surveyor will interview staff — these are expected questions and coached answers.
A3: # | B3: ACHC Interview Question | C3: Expected / Coached Answer (Key Points) | D3: Who Is Asked | E3: Staff Initials (Reviewed)
A4: 1 | B4: Did you complete on-boarding training/orientation? | C4: Yes. Completed HR New Hire Orientation (Zoom) + Dept. Orientation AHF U course + hands-on training with supervisor. On-Boarding Checklist is on file in the pharmacy and/or HR. | D4: All Staff
A5: 2 | B5: Can you describe the Chain of Command? | C5: I don't need to memorize it — the Org Chart is posted [point to it]. It shows who to report to if my immediate supervisor is unavailable. | D5: All Staff
A6: 3 | B6: Who is your Compliance Officer? | C6: Brandon Patchett, PharmD — Senior Director of Clinical Services and Pharmacy Compliance. | D6: All Staff
A7: 4 | B7: How do you report concerns or complaints from a patient? | C7: I communicate any concern to my immediate supervisor immediately. All communications must be documented. If unresolved, refer to Customer Care Line (855-894-MEDS). Pharmacy Director ensures patient safety follow-up. | D7: All Staff
A8: 5 | B8: How do you handle patients with communication or language barriers? | C8: Use Language Line (instructions are posted — I never have Language Line contact patients directly). For patients who can't read labels, I request a ScripTalk Reader. Contact supervisor or Regional Director if more support is needed. | D8: All Staff
A9: 6 | B9: What infection control procedures do you follow? | C9: Wash hands with soap and water whenever possible. Clean all equipment (counting trays, spatulas, counters) daily and document in the Daily Cleaning Log. Follow all P&P infection control precautions. Pharmacy Director completes daily Infection Control Tracking Form. | D9: All Staff
A10: 7 | B10: Are patients notified before prescriptions are processed? | C10: Yes. All patients must be notified prior to any prescription processing — most insurance companies require this, and the patient is financially responsible for any Rx processed. PSL contacts patient before every delivery. | D10: All Staff
A11: 8 | B11: Have you received a competency assessment? | C11: Yes, upon hire. Pharmacy Directors conduct routine and random competency verifications. Annual competency assessments are required. | D11: All Staff
A12: 9 | B12: What safety-related training have you received? | C12: I complete all AHF U courses assigned to me by the due date, including DME and Hazardous Drugs training annually. Various regulatory/compliance courses assigned at hire and then annually. | D12: All Staff
A13: 10 | B13: How does AHF meet patient needs during a disaster? | C13: Notify leadership at AHFRXEmergencyNotification@ahf.org immediately. Work with unaffected pharmacies to process 10-day refills and distribute. Notify patients. Within 24 hours of reopening, follow up to confirm receipt. | D13: All Staff
A14: 11 | B14: Where are Patient Rights and DMEPOS Supplier Standards found? | C14: In the Patient Welcome Booklet (pg. 7-10 for DMEPOS, pg. 14-16 for Rights). Provided to all new patients and marked in the Initial Assessment. Available on AHF Pharmacy website in English and Spanish. https://ahfpharmacy.org/wp-content/uploads/2023/04/AHFRx_PatientPacket-ACHC-Pt-advocate.pdf | D14: All Staff
A15: 12 | B15: How are after-hours calls handled? | C15: Customer Care Line (CCL) handles overflow and after-hours calls 24/7 with 24/7 pharmacist access. After-hours calls forwarded to CRC-West Pharmacists. | D15: All Staff
... A23: 20 | B23: How do patients pay and how are financial hardships handled? | C23: Patients are informed of co-pays, OOP costs, and deductibles PRIOR to processing. If unable to pay, refer to Pharmacy Director. Work with HCC Benefits Counselor and other AHF teams. Financial hardship forms are completed. | D23: All Staff

Sheet 📅 Day-Of Visit
A1: DAY-OF ACHC VISIT CHECKLIST — PHARMACY DIRECTOR
A2: Visit is UNSCHEDULED. No morning phone call. Be ready any day Jan 19 – Apr 17, 2026 (avoid Mondays).
A3: # | B3: Phase | C3: Action Item | D3: Details / Notes | E3: Done? | F3: Owner
A4: 1 | B4: OPENING | C4: Greet ACHC Surveyor professionally; introduce yourself as Pharmacy Director | D4: Confirm surveyor's credentials; offer water; keep staff calm | F4: Owner: ___
A5: 2 | B5: OPENING | C5: Participate in Opening Conference to set schedule for the day | D5: Understand what the surveyor plans to review; clarify any constraints | F5: Owner: ___
A6: 3 | B6: OPENING | C6: Designate a staff coordinator to shadow the surveyor (not answer for staff) | D6: Staff must answer independently — coordinator ensures smooth logistics only | F6: Owner: ___
A7: 4 | B7: OPENING | C7: Alert staff: ACHC visit in progress — patients still come first | D7: Brief all staff via quick huddle; remind: relax, honest answers, refer to policies | F7: Owner: ___
A8: 5 | B8: TOUR | C8: Conduct facility tour | D8: Surveyor observes layout, cleanliness, storage, signage, equipment | F8: Owner: ___
A9: 6 | B9: TOUR | C9: Confirm Org Chart is posted and visible | D9: Jan-2025 org chart must be posted or easily retrievable | F9: Owner: ___
A10: 7 | B10: TOUR | C10: Confirm Customer Care Line poster is posted in public/patient waiting area | D10: Must be clearly visible; includes 855-894-MEDS number | F10: Owner: ___
A11: 8 | B11: TOUR | C11: Confirm Language Line instructions are posted | D11: Posted with process; reminder: Language Line never contacts patient directly | F11: Owner: ___
A12: 9 | B12: TOUR | C12: Confirm Hazardous Drug storage area is labeled; Chemo Spill Kit nearby | D12: HD area clearly marked; non-HD drugs stored separately | F12: Owner: ___
A13: 10 | B13: TOUR | C13: Confirm Drug Recall Bin and Expired Medication Bin are labeled and in place | D13: Separate bins; monthly check log current | F13: Owner: ___
A14: 11 | B14: TOUR | C14: Confirm Daily Cleaning Log is current and accessible | D14: Counting trays, spatulas, Kirby Lester, counters; log up to date today | F14: Owner: ___
A15: 12 | B15: TOUR | C15: Confirm Infection Control Tracking Form is current (Pharmacy Director) | D15: Daily form completed; zero-occurrence months documented | F15: Owner: ___
... A29: 26 | B29: CLOSING | C29: Do NOT fixate on your score during the visit | D29: Deficiencies are expected and common; POC is a normal part of the process | F29: Owner: ___
